{"links":[

{"source": "Ei perusasteen jälkeistä tutkintoa, naiset 1980-1984", "target": "Yksityisen sektorin työpaikat", "value":-0.127419935239276},{"source": "Ei perusasteen jälkeistä tutkintoa, naiset 1980-1984", "target": "Palkkatulot tutkinnon suorittaneet", "value":-0.108121001308478},{"source": "Ei perusasteen jälkeistä tutkintoa, naiset 1980-1984", "target": "Syntyneet, äiti  20-29 -vuotias", "value":0.158330245556209},{"source": "Ei perusasteen jälkeistä tutkintoa, naiset 1980-1984", "target": "Työkyvyttömyysindeksi", "value":0.224103948861387},{"source": "Ei perusasteen jälkeistä tutkintoa, naiset 1980-1984", "target": "Lastenhoidon tuet", "value":0.128370302611824},{"source": "Ei perusasteen jälkeistä tutkintoa, naiset 1980-1984", "target": "Nuorisotoiminnan avustukset", "value":-0.120432003368364},{"source": "Ei perusasteen jälkeistä tutkintoa, naiset 1980-1984", "target": "Lasten pienituloisuusaste", "value":0.124954560334841},{"source": "Ei perusasteen jälkeistä tutkintoa, naiset 1980-1984", "target": "Hedelmällisyys", "value":0.149052149905957},{"source": "Ei perusasteen jälkeistä tutkintoa, naiset 1980-1984", "target": "Avioliiton solmineet miehet 25-29", "value":0.16485067488444},{"source": "Ei perusasteen jälkeistä tutkintoa, naiset 1980-1984", "target": "Vieraskieliset/1000 asukasta", "value":0.160138539101499},{"source": "Ei perusasteen jälkeistä tutkintoa, naiset 1980-1984", "target": "Kuntien välinen tulomuutto", "value":0.189295803812012},{"source": "Ei perusasteen jälkeistä tutkintoa, naiset 1980-1984", "target": "9. desiilin palkat ", "value":-0.164638429769573},{"source": "Ei perusasteen jälkeistä tutkintoa, naiset 1980-1984", "target": "Omassa seutukunnassa työssäkäyvät, %", "value":0.131257179810565},{"source": "Ei perusasteen jälkeistä tutkintoa, naiset 1980-1984", "target": "Äänestysprosentti kunnallisvaalit", "value":-0.117304338233774},{"source": "Ei perusasteen jälkeistä tutkintoa, naiset 1980-1984", "target": "Kunnan varhaiskasvatus % 1-6", "value":-0.12623835777154},{"source": "Ei perusasteen jälkeistä tutkintoa, naiset 1980-1984", "target": "Päihtyneenä väkivaltarikoksista epäillyt/1000", "value":0.142643079993442},{"source": "Ei perusasteen jälkeistä tutkintoa, naiset 1980-1984", "target": "Kelan sairastavuusindeksi", "value":0.199856589570469},{"source": "Ei perusasteen jälkeistä tutkintoa, naiset 1980-1984", "target": "Työllisyysaste, 45-54 -vuotiaat", "value":-0.132064744474995},{"source": "Ei perusasteen jälkeistä tutkintoa, naiset 1980-1984", "target": "Työllisyysaste, 18-24 -vuotiaat", "value":-0.103912443661302},{"source": "Ei perusasteen jälkeistä tutkintoa, naiset 1980-1984", "target": "Sepelvaltimotauti-indeksi", "value":0.217416394977631},{"source": "Ei perusasteen jälkeistä tutkintoa, naiset 1980-1984", "target": "Teollisuuden työpaikkojen osuus kaikista työpaikoista, %", "value":-0.111157733187379},{"source": "Ei perusasteen jälkeistä tutkintoa, naiset 1980-1984", "target": "Terveys- ja sosiaalipalvelujen työpaikkojen osuus kaikista työpaikoista, %", "value":0.133750409911141},{"source": "Ei perusasteen jälkeistä tutkintoa, naiset 1980-1984", "target": "Gini-kerroin, bruttotulot", "value":-0.222551773762897},{"source": "Ei perusasteen jälkeistä tutkintoa, naiset 1980-1984", "target": "Gini-kerroin, käytettävissä olevat tulot", "value":-0.170176680518881},{"source": "Ei perusasteen jälkeistä tutkintoa, naiset 1980-1984", "target": "Toimeentulotukea saaneet lapsiperheet, % lapsiperheistä", "value":0.139945867573934},{"source": "Ei perusasteen jälkeistä tutkintoa, naiset 1980-1984", "target": "Kokee terveydentilansa keskinkertaiseksi tai huonoksi, % 8. ja 9. luokan oppilaista", "value":-0.191479385135462},{"source": "Ei perusasteen jälkeistä tutkintoa, naiset 1980-1984", "target": "Tulot/verot 25-29 -vuotiaat", "value":-0.159897432436058},{"source": "Ei perusasteen jälkeistä tutkintoa, naiset 1980-1984", "target": "Tulot/verot 35-39 -vuotiaat", "value":0.270005489226553},{"source": "Ei perusasteen jälkeistä tutkintoa, naiset 1980-1984", "target": "Tulot/verot 70-74 -vuotiaat", "value":-0.141460261450358},{"source": "Ei perusasteen jälkeistä tutkintoa, naiset 1980-1984", "target": "Tulot/verot 75-79 -vuotiaat", "value":0.159270049586203},{"source": "Ei perusasteen jälkeistä tutkintoa, naiset 1980-1984", "target": "Tulot/verot 80-84 -vuotiaat", "value":-0.112816002815534},{"source": "Ei perusasteen jälkeistä tutkintoa, naiset 1980-1984", "target": "Työttömyysetuudet 55-59-vuotiaat", "value":-0.112165099635411},{"source": "Ei perusasteen jälkeistä tutkintoa, naiset 1980-1984", "target": "Valtion ansiotulovero 25-29-vuotiaat", "value":0.234974394685145},{"source": "Ei perusasteen jälkeistä tutkintoa, naiset 1980-1984", "target": "Valtion ansiotulovero 35-39-vuotiaat", "value":-0.208146118974613},{"source": "Ei perusasteen jälkeistä tutkintoa, naiset 1980-1984", "target": "Valtion ansiotulovero 70-74-vuotiaat", "value":0.150635568294613},{"source": "Ei perusasteen jälkeistä tutkintoa, naiset 1980-1984", "target": "Valtion ansiotulovero 80-84-vuotiaat", "value":-0.104416004291283},{"source": "Ei perusasteen jälkeistä tutkintoa, naiset 1980-1984", "target": "Valtion pääomatulovero 35-39-vuotiaat", "value":-0.128476157359694},{"source": "Ei perusasteen jälkeistä tutkintoa, naiset 1980-1984", "target": "Valtion pääomatulovero 40-44-vuotiaat", "value":0.166591767653383},{"source": "Ei perusasteen jälkeistä tutkintoa, naiset 1980-1984", "target": "Valtion pääomatulovero 45-49-vuotiaat", "value":-0.131107085524717},{"source": "Ei perusasteen jälkeistä tutkintoa, naiset 1980-1984", "target": "Kuntien välinen lähtömuutto,  20-39 -vuotiaat", "value":0.120119095971695},{"source": "Ei perusasteen jälkeistä tutkintoa, naiset 1980-1984", "target": "Kuntien välinen tulomuutto", "value":0.189295803812012},{"source": "Ei perusasteen jälkeistä tutkintoa, naiset 1980-1984", "target": "Kuntien välinen tulomuutto, 40-59 -vuotiaat", "value":0.235954221099754},{"source": "Ei perusasteen jälkeistä tutkintoa, naiset 1980-1984", "target": "Kuntien välinen tulomuutto, alle 20-vuotiaat", "value":0.187828737428125},{"source": "Ei perusasteen jälkeistä tutkintoa, naiset 1980-1984", "target": "Kuntien välinentulomuutto,  20-39 -vuotiaat", "value":0.152211669795394},{"source": "Ei perusasteen jälkeistä tutkintoa, naiset 1980-1984", "target": "Kuollutta/1000 asukasta", "value":0.145229195571269},{"source": "Ei perusasteen jälkeistä tutkintoa, naiset 1980-1984", "target": "Syntyneet, äiti  20-29 -vuotias", "value":0.158330245556209},{"source": "Ei perusasteen jälkeistä tutkintoa, naiset 1980-1984", "target": "Ulkomaalaistaustaisia", "value":0.194608726455449},{"source": "Ei perusasteen jälkeistä tutkintoa, naiset 1980-1984", "target": "Vieraskielisiä", "value":0.198598703683569},{"source": "Ei perusasteen jälkeistä tutkintoa, naiset 1980-1984", "target": "Ulkomailla syntyneitä", "value":0.218382839717059},{"source": "Ei perusasteen jälkeistä tutkintoa, naiset 1980-1984", "target": "Ulkomaan kansalaisia", "value":0.268207897386111},{"source": "Ei perusasteen jälkeistä tutkintoa, naiset 1980-1984", "target": "Yhteisöjen verotettava tulo", "value":-0.101639318429477},{"source": "Ei perusasteen jälkeistä tutkintoa, naiset 1980-1984", "target": "Äiti ja alle 3-v. lapsia", "value":0.114104268266349},{"source": "Ei perusasteen jälkeistä tutkintoa, naiset 1980-1984", "target": "Äiti ja alle 7-v. lapsia", "value":0.110512482707651},{"source": "Ei perusasteen jälkeistä tutkintoa, naiset 1980-1984", "target": "Aviopari ja alle 3-v. lapsia", "value":0.181013303358807},{"source": "Ei perusasteen jälkeistä tutkintoa, naiset 1980-1984", "target": "Aviopari ja alle 7-v. lapsia", "value":0.111951277734868},{"source": "Ei perusasteen jälkeistä tutkintoa, naiset 1980-1984", "target": "Perheisiin kuulumattomat 25-34-vuotiaat miehet", "value":0.157611926383372},{"source": "Ei perusasteen jälkeistä tutkintoa, naiset 1980-1984", "target": "Perheisiin kuulumattomat 35-44-vuotiaat miehet", "value":-0.116709684236466},{"source": "Ei perusasteen jälkeistä tutkintoa, naiset 1980-1984", "target": "Perheisiin kuulumattomat 15-24-vuotiaat naiset", "value":-0.105857227601362},{"source": "Ei perusasteen jälkeistä tutkintoa, naiset 1980-1984", "target": "Perheväestö 25-34-vuotiaat miehet", "value":0.143801993386134},{"source": "Ei perusasteen jälkeistä tutkintoa, naiset 1980-1984", "target": "Perheväestö 45-54-vuotiaat miehet", "value":-0.106542483488061},{"source": "Ei perusasteen jälkeistä tutkintoa, naiset 1980-1984", "target": "Perheväestö yli 65-vuotiaat miehet", "value":-0.113082149166535},{"source": "Ei perusasteen jälkeistä tutkintoa, naiset 1980-1984", "target": "Perheväestö 0-14-vuotiaat naiset", "value":0.11656053290287},{"source": "Ei perusasteen jälkeistä tutkintoa, naiset 1980-1984", "target": "Perheväestö 25-34-vuotiaat naiset", "value":0.14471501012735},{"source": "Ei perusasteen jälkeistä tutkintoa, naiset 1980-1984", "target": "Perheväestö 35-44-vuotiaat naiset", "value":-0.134032796206562},{"source": "Ei perusasteen jälkeistä tutkintoa, naiset 1980-1984", "target": "Avioliitosta eronneet miehet yhteensä", "value":0.144919182646963},{"source": "Ei perusasteen jälkeistä tutkintoa, naiset 1980-1984", "target": "Avioliitosta eronneet naiset 20-39-vuotiaat", "value":0.207493899160159},{"source": "Ei perusasteen jälkeistä tutkintoa, naiset 1980-1984", "target": "Solmitut avioliitot", "value":0.159126152514184},{"source": "Ei perusasteen jälkeistä tutkintoa, naiset 1980-1984", "target": "Vieraskieliset miehet", "value":0.250819148158299},{"source": "Ei perusasteen jälkeistä tutkintoa, naiset 1980-1984", "target": "Vieraskieliset naiset", "value":0.154067686213138},{"source": "Ei perusasteen jälkeistä tutkintoa, naiset 1980-1984", "target": "Miehet eronneet 20-29-vuotiaat", "value":0.133990267740717},{"source": "Ei perusasteen jälkeistä tutkintoa, naiset 1980-1984", "target": "Miehet eronneet kotimaiset kielet 20-29-vuotiaat", "value":0.161500755281718},{"source": "Ei perusasteen jälkeistä tutkintoa, naiset 1980-1984", "target": "Naiset eronneet 20-29-vuotiaat", "value":0.12689609192429},{"source": "Ei perusasteen jälkeistä tutkintoa, naiset 1980-1984", "target": "Naiset eronneet kotimaiset kielet 20-29-vuotiaat", "value":0.168681553604397},{"source": "Ei perusasteen jälkeistä tutkintoa, naiset 1980-1984", "target": "Naiset naimaton vieraskieliset 20-29-vuotiaat", "value":0.115799980762349},{"source": "Ei perusasteen jälkeistä tutkintoa, naiset 1980-1984", "target": "Miehet naimaton vieraskieliset 30-39-vuotiaat", "value":0.124287855449809},{"source": "Ei perusasteen jälkeistä tutkintoa, naiset 1980-1984", "target": "Miehet naimisissa vieraskieliset 30-39-vuotiaat", "value":0.259254260341269},{"source": "Ei perusasteen jälkeistä tutkintoa, naiset 1980-1984", "target": "Miehet eronneet vieraskieliset 30-39-vuotiaat", "value":0.132404172241445},{"source": "Ei perusasteen jälkeistä tutkintoa, naiset 1980-1984", "target": "Naiset naimaton 30-39-vuotiaat ", "value":0.31114756117225},{"source": "Ei perusasteen jälkeistä tutkintoa, naiset 1980-1984", "target": "Naiset naimisissa 30-39-vuotiaat", "value":0.104026462394842},{"source": "Ei perusasteen jälkeistä tutkintoa, naiset 1980-1984", "target": "Naiset naimaton kotimaiset kielet 30-39-vuotiaat", "value":0.28020535687656},{"source": "Ei perusasteen jälkeistä tutkintoa, naiset 1980-1984", "target": "Naiset naimaton vieraskieliset 30-39-vuotiaat", "value":0.106606933102014},{"source": "Ei perusasteen jälkeistä tutkintoa, naiset 1980-1984", "target": "Naiset naimisissa vieraskieliset 30-39-vuotiaat", "value":0.23540316012524},{"source": "Ei perusasteen jälkeistä tutkintoa, naiset 1980-1984", "target": "Naiset eronneet vieraskieliset 30-39-vuotiaat", "value":0.186411605776943},{"source": "Ei perusasteen jälkeistä tutkintoa, naiset 1980-1984", "target": "Miehet eronneet 40-49-vuotiaat", "value":-0.137793557071724},{"source": "Ei perusasteen jälkeistä tutkintoa, naiset 1980-1984", "target": "Miehet eronneet kotimaiset kielet 40-49-vuotiaat", "value":-0.158771063609645},{"source": "Ei perusasteen jälkeistä tutkintoa, naiset 1980-1984", "target": "Miehet naimaton vieraskieliset 40-49-vuotiaat", "value":0.102270247061618},{"source": "Ei perusasteen jälkeistä tutkintoa, naiset 1980-1984", "target": "Naiset naimisissa kotimaiset kielet 40-49-vuotiaat", "value":-0.106950312213252},{"source": "Ei perusasteen jälkeistä tutkintoa, naiset 1980-1984", "target": "Naiset eronneet vieraskieliset 40-49-vuotiaat", "value":-0.135971261047667},{"source": "Ei perusasteen jälkeistä tutkintoa, naiset 1980-1984", "target": "Yrittäjätulot, keskiarvo", "value":0.111090868940041},{"source": "Ei perusasteen jälkeistä tutkintoa, naiset 1980-1984", "target": "Omaisuustulot,  keskiarvo", "value":-0.129330778778648},{"source": "Ei perusasteen jälkeistä tutkintoa, naiset 1980-1984", "target": "Tuotannontekijätulot, keskiarvo", "value":-0.163818468966663},{"source": "Ei perusasteen jälkeistä tutkintoa, naiset 1980-1984", "target": "Lapsiperheiden etuudet, keskiarvo", "value":0.145679432567362},{"source": "Ei perusasteen jälkeistä tutkintoa, naiset 1980-1984", "target": "Asumisen tuet, keskiarvo", "value":0.115684418912867},{"source": "Ei perusasteen jälkeistä tutkintoa, naiset 1980-1984", "target": "Maksetut tulonsiirrot, keskiarvo", "value":-0.160770535925465},{"source": "Ei perusasteen jälkeistä tutkintoa, naiset 1980-1984", "target": "Käytettävissä oleva rahantulo, keskiarvo", "value":-0.164405628705585},{"source": "Ei perusasteen jälkeistä tutkintoa, naiset 1980-1984", "target": "IV", "value":0.109375857050328},{"source": "Ei perusasteen jälkeistä tutkintoa, naiset 1980-1984", "target": "VI", "value":0.111674802206775},{"source": "Ei perusasteen jälkeistä tutkintoa, naiset 1980-1984", "target": "X (suurituloisin 10%)", "value":-0.180607791952753},{"source": "Ei perusasteen jälkeistä tutkintoa, naiset 1980-1984", "target": "Gini-kerroin, tuotannontekijätulot", "value":-0.186844422688486},{"source": "Ei perusasteen jälkeistä tutkintoa, naiset 1980-1984", "target": "Gini-kerroin, bruttotulot", "value":-0.222551773762897},{"source": "Ei perusasteen jälkeistä tutkintoa, naiset 1980-1984", "target": "Gini-kerroin, käytettävissä olevat rahatulot", "value":-0.202700250837823},{"source": "Ei perusasteen jälkeistä tutkintoa, naiset 1980-1984", "target": "Kokonaan perusturvan varassa", "value":0.178055868288134},{"source": "Ei perusasteen jälkeistä tutkintoa, naiset 1980-1984", "target": "Kokonaan perusturvan varassa, lapsia", "value":0.182801415102197},{"source": "Ei perusasteen jälkeistä tutkintoa, naiset 1980-1984", "target": "Pitkittyneesti perusturvan varassa, lapsia", "value":0.175734699095753},{"source": "Ei perusasteen jälkeistä tutkintoa, naiset 1980-1984", "target": "Perusturvan osuus yli puolet tuloista", "value":0.102385740238726},{"source": "Ei perusasteen jälkeistä tutkintoa, naiset 1980-1984", "target": "Perusturvan osuus yli puolet tuloista, lapsia", "value":0.294353843631703},{"source": "Ei perusasteen jälkeistä tutkintoa, naiset 1980-1984", "target": "Veronalaiset tulot keskimäärin, euroa", "value":-0.209593600007719},{"source": "Ei perusasteen jälkeistä tutkintoa, naiset 1980-1984", "target": "Ansiotulot keskimäärin, euroa", "value":-0.139460841477317},{"source": "Ei perusasteen jälkeistä tutkintoa, naiset 1980-1984", "target": "Verot yhteensä keskimäärin, euroa", "value":-0.153378142149291},{"source": "Ei perusasteen jälkeistä tutkintoa, naiset 1980-1984", "target": "Valtionvero keskimäärin, euroa", "value":-0.126584516301668},{"source": "Ei perusasteen jälkeistä tutkintoa, naiset 1980-1984", "target": "Tulot miinus verot keskimäärin, euroa", "value":-0.226081115902407},{"source": "Ei perusasteen jälkeistä tutkintoa, naiset 1980-1984", "target": "Asuntovelat, euroa", "value":0.142459119643426},{"source": "Ei perusasteen jälkeistä tutkintoa, naiset 1980-1984", "target": "Velat yhteensä, euroa", "value":0.116550349911},{"source": "Ei perusasteen jälkeistä tutkintoa, naiset 1980-1984", "target": "Viranomaisten tehtävät", "value":0.123010750614072},{"source": "Ei perusasteen jälkeistä tutkintoa, naiset 1980-1984", "target": "Itsemurhan tutkinta", "value":0.182014526815262},{"source": "Ei perusasteen jälkeistä tutkintoa, naiset 1980-1984", "target": "Huumausainerikos, miehet", "value":-0.10858150268648},{"source": "Ei perusasteen jälkeistä tutkintoa, naiset 1980-1984", "target": "Kerrostalot neliöhinta (EUR/m2)", "value":0.223907492087452},{"source": "Ei perusasteen jälkeistä tutkintoa, naiset 1980-1984", "target": "Kerrostalokauppojen lukumäärä", "value":-0.107914404884499},{"source": "Ei perusasteen jälkeistä tutkintoa, naiset 1980-1984", "target": "Korkea-asteen tutkinto naiset 20-24", "value":0.1135429131315},{"source": "Ei perusasteen jälkeistä tutkintoa, naiset 1980-1984", "target": "Toisen asteen tutkinto miehet 25-29", "value":0.165774233621339},{"source": "Ei perusasteen jälkeistä tutkintoa, naiset 1980-1984", "target": "Toisen asteen tutkinto naiset 25-29", "value":0.141470393953391},{"source": "Ei perusasteen jälkeistä tutkintoa, naiset 1980-1984", "target": "Ilman perusasteen jälkeistä tutkintoa miehet 30-34 ", "value":0.275077396013475},{"source": "Ei perusasteen jälkeistä tutkintoa, naiset 1980-1984", "target": "Korkea-asteen tutkinto miehet 30-34", "value":0.21347561111113},{"source": "Ei perusasteen jälkeistä tutkintoa, naiset 1980-1984", "target": "Ilman perusasteen jälkeistä tutkintoa naiset 30-34 ", "value":0.552239838344683},{"source": "Ei perusasteen jälkeistä tutkintoa, naiset 1980-1984", "target": "Toisen asteen tutkinto naiset 30-34", "value":0.172911217461992},{"source": "Ei perusasteen jälkeistä tutkintoa, naiset 1980-1984", "target": "Korkea-asteen tutkinto miehet 35-39", "value":-0.10441872738998},{"source": "Ei perusasteen jälkeistä tutkintoa, naiset 1980-1984", "target": "Ilman perusasteen jälkeistä tutkintoa naiset 35-39 ", "value":0.109337535823022},{"source": "Ei perusasteen jälkeistä tutkintoa, naiset 1980-1984", "target": "Toisen asteen tutkinto naiset 35-39", "value":-0.187210237644999},{"source": "Ei perusasteen jälkeistä tutkintoa, naiset 1980-1984", "target": "Korkea-asteen tutkinto naiset 35-39", "value":0.17438099524194},{"source": "Ei perusasteen jälkeistä tutkintoa, naiset 1980-1984", "target": "Ilman perusasteen jälkeistä tutkintoa miehet 40-44 ", "value":0.291341990218949},{"source": "Ei perusasteen jälkeistä tutkintoa, naiset 1980-1984", "target": "Toisen asteen tutkinto naiset 40-44", "value":-0.152305588748141},{"source": "Ei perusasteen jälkeistä tutkintoa, naiset 1980-1984", "target": "Korkea-asteen tutkinto naiset 40-44", "value":-0.165168327404492},{"source": "Ei perusasteen jälkeistä tutkintoa, naiset 1980-1984", "target": "Toisen asteen tutkinto naiset 45-49", "value":0.177677977251962},{"source": "Ei perusasteen jälkeistä tutkintoa, naiset 1980-1984", "target": "Ilman perusasteen jälkeistä tutkintoa miehet 50-54 ", "value":0.110955101992013},{"source": "Ei perusasteen jälkeistä tutkintoa, naiset 1980-1984", "target": "Korkea-asteen tutkinto miehet 50-54", "value":0.101326965380625},{"source": "Ei perusasteen jälkeistä tutkintoa, naiset 1980-1984", "target": "Ilman perusasteen jälkeistä tutkintoa naiset 50-54 ", "value":-0.12432183763597},{"source": "Ei perusasteen jälkeistä tutkintoa, naiset 1980-1984", "target": "Korkea-asteen tutkinto naiset 60-64", "value":0.104680548392317},{"source": "Ei perusasteen jälkeistä tutkintoa, naiset 1980-1984", "target": "Toisen asteen tutkinto miehet 65-69", "value":0.133075168165306},{"source": "Ei perusasteen jälkeistä tutkintoa, naiset 1980-1984", "target": "Ilman perusasteen jälkeistä tutkintoa naiset 65-69 ", "value":0.282240504140656},{"source": "Ei perusasteen jälkeistä tutkintoa, naiset 1980-1984", "target": "Ilman perusasteen jälkeistä tutkintoa naiset 70-74 ", "value":-0.16256489685695},{"source": "Ei perusasteen jälkeistä tutkintoa, naiset 1980-1984", "target": "Toisen asteen tutkinto miehet 75-", "value":0.174412188590074},{"source": "Ei perusasteen jälkeistä tutkintoa, naiset 1980-1984", "target": "Korkea-asteen tutkinto miehet 75-", "value":0.144525074332025},{"source": "Ei perusasteen jälkeistä tutkintoa, naiset 1980-1984", "target": "Hedelmällisyys 20-24", "value":0.118347847253989},{"source": "Ei perusasteen jälkeistä tutkintoa, naiset 1980-1984", "target": "Hedelmällisyys 25-29", "value":0.133353314242266},{"source": "Ei perusasteen jälkeistä tutkintoa, naiset 1980-1984", "target": "Hedelmällisyys 40-44", "value":0.111280838607824},{"source": "Ei perusasteen jälkeistä tutkintoa, naiset 1980-1984", "target": "Äänestysprosentti kunnallisvaalit miehet", "value":-0.16559395076628},{"source": "Ei perusasteen jälkeistä tutkintoa, naiset 1980-1984", "target": "10. tulokymmenys", "value":-0.307658780617163},{"source": "Ei perusasteen jälkeistä tutkintoa, naiset 1980-1984", "target": "Europarlamenttivaalit vasemmiston kannatus", "value":0.107138918553218},{"source": "Ei perusasteen jälkeistä tutkintoa, naiset 1980-1984", "target": "Koulutustasomittain naiset 30-34-vuotiaat", "value":-0.289687913401863},{"source": "Ei perusasteen jälkeistä tutkintoa, naiset 1980-1984", "target": "Koulutustasomittain naiset 35-39-vuotiaat", "value":0.18931441666141},{"source": "Ei perusasteen jälkeistä tutkintoa, naiset 1980-1984", "target": "Koulutustasomittain miehet 45-49-vuotiaat", "value":0.182126555340706},{"source": "Ei perusasteen jälkeistä tutkintoa, naiset 1980-1984", "target": "Koulutustasomittain naiset 50-54-vuotiaat", "value":0.250353406948301},{"source": "Ei perusasteen jälkeistä tutkintoa, naiset 1980-1984", "target": "Koulutustasomittain naiset 55-59-vuotiaat", "value":0.186992030021494},{"source": "Ei perusasteen jälkeistä tutkintoa, naiset 1980-1984", "target": "Koulutustasomittain naiset 60-64-vuotiaat", "value":0.18751411171995},{"source": "Ei perusasteen jälkeistä tutkintoa, naiset 1980-1984", "target": "Koulutustasomittain miehet 65-69-vuotiaat", "value":0.201029014997297},{"source": "Ei perusasteen jälkeistä tutkintoa, naiset 1980-1984", "target": "Koulutustasomittain naiset 60-64-vuotiaat", "value":-0.158347833565431},{"source": "Ei perusasteen jälkeistä tutkintoa, naiset 1980-1984", "target": "Koulutustasomittain miehet yli 75-vuotiaat", "value":0.151067247096058},{"source": "Ei perusasteen jälkeistä tutkintoa, naiset 1980-1984", "target": "Koulutustasomittain naiset yli 75-vuotiaat", "value":0.105482840603087},{"source": "Ei perusasteen jälkeistä tutkintoa, naiset 1980-1984", "target": "Toimintakulut", "value":0.110923132470679},{"source": "Ei perusasteen jälkeistä tutkintoa, naiset 1980-1984", "target": "Valtionosuudet", "value":-0.120219492260324},{"source": "Ei perusasteen jälkeistä tutkintoa, naiset 1980-1984", "target": "Osuus yhteisöveron tuotosta", "value":0.103230866667884},{"source": "Ei perusasteen jälkeistä tutkintoa, naiset 1980-1984", "target": "Terveyspuntari sairastavuusindeksi", "value":0.155727189012915},{"source": "Ei perusasteen jälkeistä tutkintoa, naiset 1980-1984", "target": "Terveyspuntari kansantauti-indeksi", "value":-0.213805525743455}

]}