{"links":[

{"source": "Avoparit, joilla yli 4 alle 18v. lasta", "target": "Syntyneet, äiti  20-29 -vuotias", "value":0.108132166051069},{"source": "Avoparit, joilla yli 4 alle 18v. lasta", "target": "Koulutustasomittain", "value":-0.100886395383145},{"source": "Avoparit, joilla yli 4 alle 18v. lasta", "target": "Perhekoko, aviopari", "value":0.286183687861841},{"source": "Avoparit, joilla yli 4 alle 18v. lasta", "target": "Palkkatuki", "value":0.135090358986144},{"source": "Avoparit, joilla yli 4 alle 18v. lasta", "target": "Nuorisotoiminnan avustukset", "value":-0.107175174708176},{"source": "Avoparit, joilla yli 4 alle 18v. lasta", "target": "Toimeentulotukea yksin asuvat miehet", "value":0.11429277495401},{"source": "Avoparit, joilla yli 4 alle 18v. lasta", "target": "Alkoholijuomien myynti asukasta kohti", "value":-0.227589718186664},{"source": "Avoparit, joilla yli 4 alle 18v. lasta", "target": "Toimeentulotukea yksin asuvat naiset", "value":0.20649041635003},{"source": "Avoparit, joilla yli 4 alle 18v. lasta", "target": "Avioliiton solmineet miehet 30-34", "value":-0.106632240134885},{"source": "Avoparit, joilla yli 4 alle 18v. lasta", "target": "Erikoissairaanhoidon nettokäyttökustannukset", "value":0.104372754294308},{"source": "Avoparit, joilla yli 4 alle 18v. lasta", "target": "9. desiilin palkat ", "value":0.130497539976037},{"source": "Avoparit, joilla yli 4 alle 18v. lasta", "target": "Äänestysprosentti eduskuntavaalit miehet", "value":0.110044721666371},{"source": "Avoparit, joilla yli 4 alle 18v. lasta", "target": "Pelaa rahapelejä viikoittain % 8. ja 9. ", "value":0.161396856963388},{"source": "Avoparit, joilla yli 4 alle 18v. lasta", "target": "Gini-kerroin, käytettävissä olevat tulot", "value":0.119080109584702},{"source": "Avoparit, joilla yli 4 alle 18v. lasta", "target": "Toimeentulotukea saaneet lapsiperheet, % lapsiperheistä", "value":0.123940243356029},{"source": "Avoparit, joilla yli 4 alle 18v. lasta", "target": "Tulot/verot 30-34 -vuotiaat", "value":-0.131868122967283},{"source": "Avoparit, joilla yli 4 alle 18v. lasta", "target": "Tulot/verot 55-59 -vuotiaat", "value":-0.165759348398621},{"source": "Avoparit, joilla yli 4 alle 18v. lasta", "target": "Tulot/verot 60-64 -vuotiaat", "value":-0.176187413258156},{"source": "Avoparit, joilla yli 4 alle 18v. lasta", "target": "Tulot/verot yhteensä", "value":-0.122996324705867},{"source": "Avoparit, joilla yli 4 alle 18v. lasta", "target": "Työttömyysetuudet alle 25-vuotiaat", "value":0.114610631591894},{"source": "Avoparit, joilla yli 4 alle 18v. lasta", "target": "Työttömyysetuudet 50-54-vuotiaat", "value":0.110091770275264},{"source": "Avoparit, joilla yli 4 alle 18v. lasta", "target": "Valtion ansiotulovero 30-34-vuotiaat", "value":0.121709873967645},{"source": "Avoparit, joilla yli 4 alle 18v. lasta", "target": "Valtion ansiotulovero 60-64-vuotiaat", "value":0.128057194145662},{"source": "Avoparit, joilla yli 4 alle 18v. lasta", "target": "Valtion pääomatulovero 25-29-vuotiaat", "value":-0.108314472142329},{"source": "Avoparit, joilla yli 4 alle 18v. lasta", "target": "Valtion pääomatulovero 55-59-vuotiaat", "value":0.440437385990753},{"source": "Avoparit, joilla yli 4 alle 18v. lasta", "target": "Syntyneet, äiti  20-29 -vuotias", "value":0.108132166051069},{"source": "Avoparit, joilla yli 4 alle 18v. lasta", "target": "Avopari ja lapsia", "value":0.186665920131695},{"source": "Avoparit, joilla yli 4 alle 18v. lasta", "target": "Avopari ja alle 3-v. lapsia", "value":0.133713762318339},{"source": "Avoparit, joilla yli 4 alle 18v. lasta", "target": "Avopari ja alle 7-v. lapsia", "value":0.156928138137639},{"source": "Avoparit, joilla yli 4 alle 18v. lasta", "target": "Perheisiin kuulumattomat 25-34-vuotiaat miehet", "value":-0.112283958781608},{"source": "Avoparit, joilla yli 4 alle 18v. lasta", "target": "Perheisiin kuulumattomat 55-64-vuotiaat miehet", "value":0.101723212766009},{"source": "Avoparit, joilla yli 4 alle 18v. lasta", "target": "Perheisiin kuulumattomat 35-44-vuotiaat naiset", "value":0.107083812871089},{"source": "Avoparit, joilla yli 4 alle 18v. lasta", "target": "Perheväestö 0-14-vuotiaat naiset", "value":0.168779565904378},{"source": "Avoparit, joilla yli 4 alle 18v. lasta", "target": "Avioliitosta eronneet miehet yhteensä", "value":-0.120331897279032},{"source": "Avoparit, joilla yli 4 alle 18v. lasta", "target": "Avioliitosta eronneet miehet 20-39-vuotiaat", "value":-0.110906247188012},{"source": "Avoparit, joilla yli 4 alle 18v. lasta", "target": "Avioliitosta eronneet naiset 20-39-vuotiaat", "value":-0.109854820201022},{"source": "Avoparit, joilla yli 4 alle 18v. lasta", "target": "Vieraskieliset miehet", "value":-0.100395113866286},{"source": "Avoparit, joilla yli 4 alle 18v. lasta", "target": "Miehet eronneet kotimaiset kielet 20-29-vuotiaat", "value":0.146059490460679},{"source": "Avoparit, joilla yli 4 alle 18v. lasta", "target": "Miehet eronneet vieraskieliset 20-29-vuotiaat", "value":-0.101187789952253},{"source": "Avoparit, joilla yli 4 alle 18v. lasta", "target": "Miehet naimaton vieraskieliset 30-39-vuotiaat", "value":-0.133700106863275},{"source": "Avoparit, joilla yli 4 alle 18v. lasta", "target": "Miehet eronneet vieraskieliset 30-39-vuotiaat", "value":-0.136948272822507},{"source": "Avoparit, joilla yli 4 alle 18v. lasta", "target": "Naiset eronneet 40-49-vuotiaat", "value":0.147555493532069},{"source": "Avoparit, joilla yli 4 alle 18v. lasta", "target": "Naiset eronneet kotimaiset kielet 40-49-vuotiaat", "value":0.143530344990655},{"source": "Avoparit, joilla yli 4 alle 18v. lasta", "target": "Yrittäjätulot, keskiarvo", "value":-0.140736503349725},{"source": "Avoparit, joilla yli 4 alle 18v. lasta", "target": "Yrittäjätulot metsätaloudesta, keskiarvo", "value":-0.138150208123494},{"source": "Avoparit, joilla yli 4 alle 18v. lasta", "target": "Lapsiperheiden etuudet, keskiarvo", "value":0.102397526436071},{"source": "Avoparit, joilla yli 4 alle 18v. lasta", "target": "Maksetut tulonsiirrot, keskiarvo", "value":0.113755236722551},{"source": "Avoparit, joilla yli 4 alle 18v. lasta", "target": "IV-tulodesiili", "value":0.104550789267205},{"source": "Avoparit, joilla yli 4 alle 18v. lasta", "target": "Gini-kerroin, tuotannontekijätulot", "value":0.131009864946625},{"source": "Avoparit, joilla yli 4 alle 18v. lasta", "target": "Verot yhteensä keskimäärin, euroa", "value":0.124452512599377},{"source": "Avoparit, joilla yli 4 alle 18v. lasta", "target": "Pahoinpitely, miehet", "value":0.346620360578884},{"source": "Avoparit, joilla yli 4 alle 18v. lasta", "target": "Pahoinpitely, naiset", "value":-0.116271023592663},{"source": "Avoparit, joilla yli 4 alle 18v. lasta", "target": "Puun myyntitulot metsäverotuksessa", "value":-0.10672523136379},{"source": "Avoparit, joilla yli 4 alle 18v. lasta", "target": "Kerrostalot neliöhinta (EUR/m2)", "value":0.139252425168153},{"source": "Avoparit, joilla yli 4 alle 18v. lasta", "target": "Toisen asteen tutkinto miehet 20-24", "value":0.111380367828278},{"source": "Avoparit, joilla yli 4 alle 18v. lasta", "target": "Toisen asteen tutkinto naiset 20-24", "value":0.107494844818901},{"source": "Avoparit, joilla yli 4 alle 18v. lasta", "target": "Korkea-asteen tutkinto naiset 20-24", "value":0.113753797365325},{"source": "Avoparit, joilla yli 4 alle 18v. lasta", "target": "Korkea-asteen tutkinto naiset 25-29", "value":0.112164363727071},{"source": "Avoparit, joilla yli 4 alle 18v. lasta", "target": "Toisen asteen tutkinto miehet 50-54", "value":0.139513977687036},{"source": "Avoparit, joilla yli 4 alle 18v. lasta", "target": "Ilman perusasteen jälkeistä tutkintoa naiset 50-54 ", "value":0.126187799753407},{"source": "Avoparit, joilla yli 4 alle 18v. lasta", "target": "Toisen asteen tutkinto miehet 60-64", "value":0.137743029636198},{"source": "Avoparit, joilla yli 4 alle 18v. lasta", "target": "Toisen asteen tutkinto miehet 65-69", "value":-0.109066709189471},{"source": "Avoparit, joilla yli 4 alle 18v. lasta", "target": "Ilman perusasteen jälkeistä tutkintoa naiset 70-74 ", "value":0.136551191686483},{"source": "Avoparit, joilla yli 4 alle 18v. lasta", "target": "Hedelmällisyys 20-24", "value":0.158743069855235},{"source": "Avoparit, joilla yli 4 alle 18v. lasta", "target": "Hedelmällisyys 30-34", "value":0.105263499592791},{"source": "Avoparit, joilla yli 4 alle 18v. lasta", "target": "Hedelmällisyys 40-49", "value":-0.135135508409665},{"source": "Avoparit, joilla yli 4 alle 18v. lasta", "target": "Koulutustasomittain miehet 20-24-vuotiaat", "value":0.102429984408812},{"source": "Avoparit, joilla yli 4 alle 18v. lasta", "target": "Koulutustasomittain naiset 60-64-vuotiaat", "value":0.138947245031774},{"source": "Avoparit, joilla yli 4 alle 18v. lasta", "target": "Koulutustasomittain naiset 70-74-vuotiaat", "value":-0.149762585588585},{"source": "Avoparit, joilla yli 4 alle 18v. lasta", "target": "Osuus yhteisöveron tuotosta", "value":0.124515946681139},{"source": "Avoparit, joilla yli 4 alle 18v. lasta", "target": "Terveyspuntari sairastavuusindeksi", "value":-0.12932860053065},{"source": "Avoparit, joilla yli 4 alle 18v. lasta", "target": "Ei perusasteen jälkeistä tutkintoa, naiset 1985-1989", "value":0.163742234972956},{"source": "Avoparit, joilla yli 4 alle 18v. lasta", "target": "Ulkomaan kansalaiset miehet, eurooppalaiset", "value":-0.104727256972929}

]}