{"links":[

{"source": "Kuntoutus, mielenterveyden ja käyttäytymisen häiriöt, yhteensä", "target": "THL:n sairastavuusindeksi", "value":0.142465260825199},{"source": "Kuntoutus, mielenterveyden ja käyttäytymisen häiriöt, yhteensä", "target": "Koulutustasomittain", "value":-0.106485240263096},{"source": "Kuntoutus, mielenterveyden ja käyttäytymisen häiriöt, yhteensä", "target": "Kelan maksamat tuet", "value":0.202107732142309},{"source": "Kuntoutus, mielenterveyden ja käyttäytymisen häiriöt, yhteensä", "target": "Avioliiton solmineet miehet 20-24", "value":-0.145444354163218},{"source": "Kuntoutus, mielenterveyden ja käyttäytymisen häiriöt, yhteensä", "target": "Avioliiton solmineet naiset 20-24", "value":0.104747128255356},{"source": "Kuntoutus, mielenterveyden ja käyttäytymisen häiriöt, yhteensä", "target": "Toimeentulotukea yksin asuvat naiset", "value":0.119160126824723},{"source": "Kuntoutus, mielenterveyden ja käyttäytymisen häiriöt, yhteensä", "target": "Ei perusasteen jälkeistä tutkintoa, 20+ -vuotiaat miehet", "value":0.107521796829306},{"source": "Kuntoutus, mielenterveyden ja käyttäytymisen häiriöt, yhteensä", "target": "Ei perusasteen jälkeistä tutkintoa, 20+ -vuotiaat naiset", "value":0.124300592046837},{"source": "Kuntoutus, mielenterveyden ja käyttäytymisen häiriöt, yhteensä", "target": "Korkea-asteen tutkinnon suorittaneet, 20+ -vuotiaat naiset", "value":0.118340964216737},{"source": "Kuntoutus, mielenterveyden ja käyttäytymisen häiriöt, yhteensä", "target": "Kuntoutuspalvelukustannukset", "value":0.278433922917736},{"source": "Kuntoutus, mielenterveyden ja käyttäytymisen häiriöt, yhteensä", "target": "1. desiilin palkat", "value":-0.115040305476007},{"source": "Kuntoutus, mielenterveyden ja käyttäytymisen häiriöt, yhteensä", "target": "Sisäänpendelöinti, % alueella työssäkäyvistä", "value":-0.11651582289755},{"source": "Kuntoutus, mielenterveyden ja käyttäytymisen häiriöt, yhteensä", "target": "Äänestysprosentti eduskuntavaalit miehet", "value":0.107513844255425},{"source": "Kuntoutus, mielenterveyden ja käyttäytymisen häiriöt, yhteensä", "target": "Kuntien välinen tulomuutto, 40-59 -vuotiaat", "value":-0.123208225814248},{"source": "Kuntoutus, mielenterveyden ja käyttäytymisen häiriöt, yhteensä", "target": "Työllisyysaste, 25-34 -vuotiaat", "value":-0.166085186079977},{"source": "Kuntoutus, mielenterveyden ja käyttäytymisen häiriöt, yhteensä", "target": "Kunnallisvaalit vasemmiston kannatus", "value":-0.14146673857282},{"source": "Kuntoutus, mielenterveyden ja käyttäytymisen häiriöt, yhteensä", "target": "Kunnallisvaalit keskustan kannatus", "value":0.135070970359086},{"source": "Kuntoutus, mielenterveyden ja käyttäytymisen häiriöt, yhteensä", "target": "Lääkekorvausoikeudet, vaikeat psykoosit ja mielenterveyshäiriöt", "value":0.108859025974559},{"source": "Kuntoutus, mielenterveyden ja käyttäytymisen häiriöt, yhteensä", "target": "Tulot/verot 30-34 -vuotiaat", "value":0.121944018738179},{"source": "Kuntoutus, mielenterveyden ja käyttäytymisen häiriöt, yhteensä", "target": "Tulot/verot 50-54 -vuotiaat", "value":-0.106853266822459},{"source": "Kuntoutus, mielenterveyden ja käyttäytymisen häiriöt, yhteensä", "target": "Tulot/verot 70-74 -vuotiaat", "value":0.145561038731618},{"source": "Kuntoutus, mielenterveyden ja käyttäytymisen häiriöt, yhteensä", "target": "Valtion ansiotulovero yhteensä", "value":0.161651816936768},{"source": "Kuntoutus, mielenterveyden ja käyttäytymisen häiriöt, yhteensä", "target": "Valtion ansiotulovero 30-34-vuotiaat", "value":-0.104541232749317},{"source": "Kuntoutus, mielenterveyden ja käyttäytymisen häiriöt, yhteensä", "target": "Valtion ansiotulovero 40-44-vuotiaat", "value":0.113940491356066},{"source": "Kuntoutus, mielenterveyden ja käyttäytymisen häiriöt, yhteensä", "target": "Valtion ansiotulovero 45-49-vuotiaat", "value":0.137571448996556},{"source": "Kuntoutus, mielenterveyden ja käyttäytymisen häiriöt, yhteensä", "target": "Valtion ansiotulovero 50-54-vuotiaat", "value":0.107265676767819},{"source": "Kuntoutus, mielenterveyden ja käyttäytymisen häiriöt, yhteensä", "target": "Valtion ansiotulovero 70-74-vuotiaat", "value":-0.102813673512663},{"source": "Kuntoutus, mielenterveyden ja käyttäytymisen häiriöt, yhteensä", "target": "Valtion ansiotulovero 80-84-vuotiaat", "value":0.137078449858048},{"source": "Kuntoutus, mielenterveyden ja käyttäytymisen häiriöt, yhteensä", "target": "Valtion ansiotulovero yli 85-vuotiaat", "value":-0.180489337050383},{"source": "Kuntoutus, mielenterveyden ja käyttäytymisen häiriöt, yhteensä", "target": "Valtion pääomatulovero 35-39-vuotiaat", "value":0.103908350699125},{"source": "Kuntoutus, mielenterveyden ja käyttäytymisen häiriöt, yhteensä", "target": "Valtion pääomatulovero 45-49-vuotiaat", "value":0.109159451018646},{"source": "Kuntoutus, mielenterveyden ja käyttäytymisen häiriöt, yhteensä", "target": "Valtion pääomatulovero 65-69-vuotiaat", "value":0.108403428645305},{"source": "Kuntoutus, mielenterveyden ja käyttäytymisen häiriöt, yhteensä", "target": "Valtion pääomatulovero 75-79-vuotiaat", "value":-0.120023534681713},{"source": "Kuntoutus, mielenterveyden ja käyttäytymisen häiriöt, yhteensä", "target": "Asuntokunnan koko (3 henkilöä)", "value":0.144137151377689},{"source": "Kuntoutus, mielenterveyden ja käyttäytymisen häiriöt, yhteensä", "target": "Kuntien välinen tulomuutto, 60+ -vuotiaat", "value":-0.169181781198866},{"source": "Kuntoutus, mielenterveyden ja käyttäytymisen häiriöt, yhteensä", "target": "Lääkekorvausoikeudet, krooninen verenpainetauti", "value":0.100930199865882},{"source": "Kuntoutus, mielenterveyden ja käyttäytymisen häiriöt, yhteensä", "target": "Syntyneet, äiti alle 20-vuotias", "value":-0.10586698143428},{"source": "Kuntoutus, mielenterveyden ja käyttäytymisen häiriöt, yhteensä", "target": "Yrittäjät, naiset", "value":0.150907714186451},{"source": "Kuntoutus, mielenterveyden ja käyttäytymisen häiriöt, yhteensä", "target": "Vieraskielisiä", "value":0.101966784052089},{"source": "Kuntoutus, mielenterveyden ja käyttäytymisen häiriöt, yhteensä", "target": "Ulkomailla syntyneitä", "value":0.106824207619756},{"source": "Kuntoutus, mielenterveyden ja käyttäytymisen häiriöt, yhteensä", "target": "Ulkomaan kansalaisia", "value":0.12951258722454},{"source": "Kuntoutus, mielenterveyden ja käyttäytymisen häiriöt, yhteensä", "target": "Avopari ja lapsia", "value":0.107021248427662},{"source": "Kuntoutus, mielenterveyden ja käyttäytymisen häiriöt, yhteensä", "target": "Avopari ja alle 7-v. lapsia", "value":0.168790954453007},{"source": "Kuntoutus, mielenterveyden ja käyttäytymisen häiriöt, yhteensä", "target": "Avioparit, joilla yli 3 alle 7v. lasta", "value":-0.107952870722141},{"source": "Kuntoutus, mielenterveyden ja käyttäytymisen häiriöt, yhteensä", "target": "Perheisiin kuulumattomat 0-14-vuotiaat miehet", "value":-0.195087274405802},{"source": "Kuntoutus, mielenterveyden ja käyttäytymisen häiriöt, yhteensä", "target": "Perheisiin kuulumattomat 35-44-vuotiaat miehet", "value":0.110177664764234},{"source": "Kuntoutus, mielenterveyden ja käyttäytymisen häiriöt, yhteensä", "target": "Perheisiin kuulumattomat 45-54-vuotiaat naiset", "value":0.143538778643817},{"source": "Kuntoutus, mielenterveyden ja käyttäytymisen häiriöt, yhteensä", "target": "Perheväestö 0-14-vuotiaat miehet", "value":0.131765178596579},{"source": "Kuntoutus, mielenterveyden ja käyttäytymisen häiriöt, yhteensä", "target": "Perheväestö 35-44-vuotiaat miehet", "value":0.11004033225582},{"source": "Kuntoutus, mielenterveyden ja käyttäytymisen häiriöt, yhteensä", "target": "Perheväestö yli 65-vuotiaat miehet", "value":0.185578831050284},{"source": "Kuntoutus, mielenterveyden ja käyttäytymisen häiriöt, yhteensä", "target": "Perheväestö 0-14-vuotiaat naiset", "value":0.142132746680207},{"source": "Kuntoutus, mielenterveyden ja käyttäytymisen häiriöt, yhteensä", "target": "Perheväestö 35-44-vuotiaat naiset", "value":0.125790613664265},{"source": "Kuntoutus, mielenterveyden ja käyttäytymisen häiriöt, yhteensä", "target": "Perheväestö 55-64-vuotiaat naiset", "value":0.152211270335389},{"source": "Kuntoutus, mielenterveyden ja käyttäytymisen häiriöt, yhteensä", "target": "Perheväestö yli 65-vuotiaat naiset", "value":0.181200547835878},{"source": "Kuntoutus, mielenterveyden ja käyttäytymisen häiriöt, yhteensä", "target": "Perheväestö miehet yhteensä", "value":0.141156072162472},{"source": "Kuntoutus, mielenterveyden ja käyttäytymisen häiriöt, yhteensä", "target": "Perheväestö naiset yhteensä", "value":0.157159886610006},{"source": "Kuntoutus, mielenterveyden ja käyttäytymisen häiriöt, yhteensä", "target": "Avioliitosta eronneet miehet 20-39-vuotiaat", "value":0.104504835346775},{"source": "Kuntoutus, mielenterveyden ja käyttäytymisen häiriöt, yhteensä", "target": "Solmitut avioliitot", "value":-0.130727542922658},{"source": "Kuntoutus, mielenterveyden ja käyttäytymisen häiriöt, yhteensä", "target": "Miehet naimaton 20-29-vuotiaat ", "value":0.10044155213093},{"source": "Kuntoutus, mielenterveyden ja käyttäytymisen häiriöt, yhteensä", "target": "Miehet naimisissa 20-29-vuotiaat", "value":-0.105756506937635},{"source": "Kuntoutus, mielenterveyden ja käyttäytymisen häiriöt, yhteensä", "target": "Miehet naimaton vieraskieliset 20-29-vuotiaat", "value":0.120419279207282},{"source": "Kuntoutus, mielenterveyden ja käyttäytymisen häiriöt, yhteensä", "target": "Naiset naimaton 20-29-vuotiaat ", "value":0.160832261717401},{"source": "Kuntoutus, mielenterveyden ja käyttäytymisen häiriöt, yhteensä", "target": "Naiset naimaton kotimaiset kielet 20-29-vuotiaat", "value":0.145180153691634},{"source": "Kuntoutus, mielenterveyden ja käyttäytymisen häiriöt, yhteensä", "target": "Miehet eronneet vieraskieliset 30-39-vuotiaat", "value":-0.101836935660259},{"source": "Kuntoutus, mielenterveyden ja käyttäytymisen häiriöt, yhteensä", "target": "Miehet naimaton 40-49-vuotiaat ", "value":0.129415745647388},{"source": "Kuntoutus, mielenterveyden ja käyttäytymisen häiriöt, yhteensä", "target": "Miehet naimisissa 40-49-vuotiaat", "value":0.181012077839927},{"source": "Kuntoutus, mielenterveyden ja käyttäytymisen häiriöt, yhteensä", "target": "Miehet naimaton kotimaiset kielet 40-49-vuotiaat", "value":0.100060031983649},{"source": "Kuntoutus, mielenterveyden ja käyttäytymisen häiriöt, yhteensä", "target": "Miehet naimisissa kotimaiset kielet 40-49-vuotiaat", "value":0.176080902379179},{"source": "Kuntoutus, mielenterveyden ja käyttäytymisen häiriöt, yhteensä", "target": "Miehet eronneet vieraskieliset 40-49-vuotiaat", "value":0.138898234217436},{"source": "Kuntoutus, mielenterveyden ja käyttäytymisen häiriöt, yhteensä", "target": "Naiset naimaton 40-49-vuotiaat ", "value":0.11809307210282},{"source": "Kuntoutus, mielenterveyden ja käyttäytymisen häiriöt, yhteensä", "target": "Naiset naimisissa 40-49-vuotiaat", "value":0.182391169699009},{"source": "Kuntoutus, mielenterveyden ja käyttäytymisen häiriöt, yhteensä", "target": "Naiset naimaton kotimaiset kielet 40-49-vuotiaat", "value":0.108862115176383},{"source": "Kuntoutus, mielenterveyden ja käyttäytymisen häiriöt, yhteensä", "target": "Naiset naimisissa kotimaiset kielet 40-49-vuotiaat", "value":0.174794184647173},{"source": "Kuntoutus, mielenterveyden ja käyttäytymisen häiriöt, yhteensä", "target": "Verot ansiotuloista, keskiarvo", "value":0.113253904148089},{"source": "Kuntoutus, mielenterveyden ja käyttäytymisen häiriöt, yhteensä", "target": "Käytettävissä oleva rahatulo, mediaani", "value":0.115262913481883},{"source": "Kuntoutus, mielenterveyden ja käyttäytymisen häiriöt, yhteensä", "target": "III-tulodesiili", "value":0.112625618325282},{"source": "Kuntoutus, mielenterveyden ja käyttäytymisen häiriöt, yhteensä", "target": "V (keskituloisin 10 %)", "value":0.114817845878646},{"source": "Kuntoutus, mielenterveyden ja käyttäytymisen häiriöt, yhteensä", "target": "IX-tulodesiili", "value":0.103354428075612},{"source": "Kuntoutus, mielenterveyden ja käyttäytymisen häiriöt, yhteensä", "target": "Lääkekorvausoikeudet, munuaisten vajaatoiminta", "value":0.11032027473883},{"source": "Kuntoutus, mielenterveyden ja käyttäytymisen häiriöt, yhteensä", "target": "Pitkittyneesti perusturvan varassa, lapsia", "value":-0.105528100947761},{"source": "Kuntoutus, mielenterveyden ja käyttäytymisen häiriöt, yhteensä", "target": "Perusturvan osuus yli puolet tuloista", "value":0.130448905950831},
{"source": "Kuntoutus, mielenterveyden ja käyttäytymisen häiriöt, yhteensä", "target": "Tulonsaajia", "value":0.16608072469522},{"source": "Kuntoutus, mielenterveyden ja käyttäytymisen häiriöt, yhteensä", "target": "Velat yhteensä, euroa", "value":0.10252487936533},{"source": "Kuntoutus, mielenterveyden ja käyttäytymisen häiriöt, yhteensä", "target": "Rattijuopumus, naiset", "value":-0.105530421677498},{"source": "Kuntoutus, mielenterveyden ja käyttäytymisen häiriöt, yhteensä", "target": "Pinta-ala/henkilö, m2", "value":-0.180324698738982},{"source": "Kuntoutus, mielenterveyden ja käyttäytymisen häiriöt, yhteensä", "target": "Toisen asteen tutkinto naiset 20-24", "value":0.107640826044773},{"source": "Kuntoutus, mielenterveyden ja käyttäytymisen häiriöt, yhteensä", "target": "Toisen asteen tutkinto miehet 30-34", "value":-0.114242712343337},{"source": "Kuntoutus, mielenterveyden ja käyttäytymisen häiriöt, yhteensä", "target": "Toisen asteen tutkinto naiset 30-34", "value":-0.111791346085572},{"source": "Kuntoutus, mielenterveyden ja käyttäytymisen häiriöt, yhteensä", "target": "Korkea-asteen tutkinto naiset 40-44", "value":0.12378114965012},{"source": "Kuntoutus, mielenterveyden ja käyttäytymisen häiriöt, yhteensä", "target": "Ilman perusasteen jälkeistä tutkintoa miehet 45-49 ", "value":0.107635365341524},{"source": "Kuntoutus, mielenterveyden ja käyttäytymisen häiriöt, yhteensä", "target": "Toisen asteen tutkinto miehet 45-49", "value":0.138244757173922},{"source": "Kuntoutus, mielenterveyden ja käyttäytymisen häiriöt, yhteensä", "target": "Korkea-asteen tutkinto miehet 45-49", "value":-0.187261165911724},{"source": "Kuntoutus, mielenterveyden ja käyttäytymisen häiriöt, yhteensä", "target": "Ilman perusasteen jälkeistä tutkintoa miehet 70-74 ", "value":0.121769661534911},{"source": "Kuntoutus, mielenterveyden ja käyttäytymisen häiriöt, yhteensä", "target": "Korkea-asteen tutkinto miehet 70-74", "value":-0.140233692260691},{"source": "Kuntoutus, mielenterveyden ja käyttäytymisen häiriöt, yhteensä", "target": "Korkea-asteen tutkinto miehet 75-", "value":0.117029424717028},{"source": "Kuntoutus, mielenterveyden ja käyttäytymisen häiriöt, yhteensä", "target": "Hedelmällisyys 15-19", "value":0.161619044766053},{"source": "Kuntoutus, mielenterveyden ja käyttäytymisen häiriöt, yhteensä", "target": "Hedelmällisyys 25-29", "value":-0.184674650826713},{"source": "Kuntoutus, mielenterveyden ja käyttäytymisen häiriöt, yhteensä", "target": "Hedelmällisyys 45-49", "value":-0.323190061597921},{"source": "Kuntoutus, mielenterveyden ja käyttäytymisen häiriöt, yhteensä", "target": "Koulutustasomittain miehet 45-49-vuotiaat", "value":-0.177668550504396},{"source": "Kuntoutus, mielenterveyden ja käyttäytymisen häiriöt, yhteensä", "target": "Koulutustasomittain naiset 60-64-vuotiaat", "value":-0.120795337117619},{"source": "Kuntoutus, mielenterveyden ja käyttäytymisen häiriöt, yhteensä", "target": "Koulutustasomittain miehet 70-74-vuotiaat", "value":-0.185640176449059},{"source": "Kuntoutus, mielenterveyden ja käyttäytymisen häiriöt, yhteensä", "target": "Koulutustasomittain miehet yhteensä", "value":-0.114434344690322},{"source": "Kuntoutus, mielenterveyden ja käyttäytymisen häiriöt, yhteensä", "target": "Asukasluku", "value":0.131665181553838},{"source": "Kuntoutus, mielenterveyden ja käyttäytymisen häiriöt, yhteensä", "target": "Vuosikate", "value":0.101200180866345},{"source": "Kuntoutus, mielenterveyden ja käyttäytymisen häiriöt, yhteensä", "target": "Suunnitelman mukaiset poistot ja arvonalet", "value":-0.148113979019287},{"source": "Kuntoutus, mielenterveyden ja käyttäytymisen häiriöt, yhteensä", "target": "Tuloveroprosentti", "value":-0.240528468204022},{"source": "Kuntoutus, mielenterveyden ja käyttäytymisen häiriöt, yhteensä", "target": "Asuntokuntaväestö tulokymmenyksessä, henkilöä keskituloisin 10 %", "value":0.114817845878646},{"source": "Kuntoutus, mielenterveyden ja käyttäytymisen häiriöt, yhteensä", "target": "Työlliset, 35-44-vuotiaat", "value":0.149376599197991},{"source": "Kuntoutus, mielenterveyden ja käyttäytymisen häiriöt, yhteensä", "target": "Ulkomaan kansalaiset, eurooppalaiset", "value":0.117093400393709},{"source": "Kuntoutus, mielenterveyden ja käyttäytymisen häiriöt, yhteensä", "target": "Ulkomaan kansalaiset miehet, eurooppalaiset", "value":0.118664699288007},{"source": "Kuntoutus, mielenterveyden ja käyttäytymisen häiriöt, yhteensä", "target": "Väestö, kaupunkialueet", "value":0.125355619565696},{"source": "Kuntoutus, mielenterveyden ja käyttäytymisen häiriöt, yhteensä", "target": "Työkyvyttömyyseläke, mielenterveyden ja käyttäytymisen häiriöt 30-34 v", "value":0.160089115368475},{"source": "Kuntoutus, mielenterveyden ja käyttäytymisen häiriöt, yhteensä", "target": "Työkyvyttömyyseläke, tuki- ja liikuntaelinten sairaudet 55-59 v", "value":-0.139496654826896},{"source": "Kuntoutus, mielenterveyden ja käyttäytymisen häiriöt, yhteensä", "target": "Työkyvyttömyyseläke, miehet 30-34 v", "value":0.130129150822253},{"source": "Kuntoutus, mielenterveyden ja käyttäytymisen häiriöt, yhteensä", "target": "Työkyvyttömyyseläke, miehet 50-54 v", "value":0.10607964129793},{"source": "Kuntoutus, mielenterveyden ja käyttäytymisen häiriöt, yhteensä", "target": "Työkyvyttömyyseläke, naiset 20-24 v", "value":-0.194396053114072},{"source": "Kuntoutus, mielenterveyden ja käyttäytymisen häiriöt, yhteensä", "target": "Voimassaolevat lääkekorvausoikeudet 0-4 v", "value":0.128358968170578},{"source": "Kuntoutus, mielenterveyden ja käyttäytymisen häiriöt, yhteensä", "target": "Voimassaolevat lääkekorvausoikeudet 90-94 v", "value":-0.146755635166547},{"source": "Kuntoutus, mielenterveyden ja käyttäytymisen häiriöt, yhteensä", "target": "Kaikki eläkkeensaajat yhteensä", "value":0.124626881748626},{"source": "Kuntoutus, mielenterveyden ja käyttäytymisen häiriöt, yhteensä", "target": "Kaikki eläkkeensaajat 0-4 v", "value":0.298586902887782},{"source": "Kuntoutus, mielenterveyden ja käyttäytymisen häiriöt, yhteensä", "target": "Kaikki eläkkeensaajat 5-9 v", "value":0.103081586795479},{"source": "Kuntoutus, mielenterveyden ja käyttäytymisen häiriöt, yhteensä", "target": "Kaikki eläkkeensaajat 25-29 v", "value":-0.136889454188425},{"source": "Kuntoutus, mielenterveyden ja käyttäytymisen häiriöt, yhteensä", "target": "Kaikki eläkkeensaajat 70-74 v", "value":0.129861876533367},{"source": "Kuntoutus, mielenterveyden ja käyttäytymisen häiriöt, yhteensä", "target": "Kaikki eläkkeensaajat 80-84 v", "value":0.132179805795585},{"source": "Kuntoutus, mielenterveyden ja käyttäytymisen häiriöt, yhteensä", "target": "Kaikki eläkkeensaajat 90-94 v", "value":-0.133431874215116},{"source": "Kuntoutus, mielenterveyden ja käyttäytymisen häiriöt, yhteensä", "target": "Kaikki eläkkeensaajat yli 99 v", "value":0.123880677307494},{"source": "Kuntoutus, mielenterveyden ja käyttäytymisen häiriöt, yhteensä", "target": "Aktiivitoimenpiteissä aloittaneet miehet yhteensä", "value":-0.15401901463275},{"source": "Kuntoutus, mielenterveyden ja käyttäytymisen häiriöt, yhteensä", "target": "Aktiivitoimenpiteissä aloittaneet miehet työvoimakoulutus", "value":-0.114785180777826},{"source": "Kuntoutus, mielenterveyden ja käyttäytymisen häiriöt, yhteensä", "target": "Työmarkkinatuki korvatut päivät yli 1000 miehet 20-24 v", "value":-0.995786991507629},{"source": "Kuntoutus, mielenterveyden ja käyttäytymisen häiriöt, yhteensä", "target": "Työmarkkinatuki korvatut päivät yli 1000 naiset 20-24 v", "value":-0.98186259959513},{"source": "Kuntoutus, mielenterveyden ja käyttäytymisen häiriöt, yhteensä", "target": "Työmarkkinatuki korvatut päivät yli 1000 naiset 25-29 v", "value":0.207715489160237},{"source": "Kuntoutus, mielenterveyden ja käyttäytymisen häiriöt, yhteensä", "target": "Työmarkkinatuki korvatut päivät yli 1000 miehet 40-44 v", "value":0.100312099548967},{"source": "Kuntoutus, mielenterveyden ja käyttäytymisen häiriöt, yhteensä", "target": "Työmarkkinatuki korvatut päivät yli 1000 naiset 50-54 v", "value":0.110990216291208},{"source": "Kuntoutus, mielenterveyden ja käyttäytymisen häiriöt, yhteensä", "target": "Työmarkkinatuki korvatut päivät yli 1000 miehet 55-59 v", "value":-0.112156393526058},{"source": "Kuntoutus, mielenterveyden ja käyttäytymisen häiriöt, yhteensä", "target": "Työmarkkinatuki korvatut päivät yli 1000 naiset 55-59 v", "value":-0.107925044777895},{"source": "Kuntoutus, mielenterveyden ja käyttäytymisen häiriöt, yhteensä", "target": "Työmarkkinatuki korvatut päivät yli 1000 miehet 60-64 v", "value":0.102033453814582},{"source": "Kuntoutus, mielenterveyden ja käyttäytymisen häiriöt, yhteensä", "target": "Työmarkkinatuki korvatut päivät yli 1000 naiset 60-64 v", "value":-0.129607347452347},{"source": "Kuntoutus, mielenterveyden ja käyttäytymisen häiriöt, yhteensä", "target": "Sairauspäivärahojen korvatut päivät miehet 20-24 v ", "value":-0.20190668185935},{"source": "Kuntoutus, mielenterveyden ja käyttäytymisen häiriöt, yhteensä", "target": "Erityishoitorahan saajat, lapset", "value":0.143026093774389},{"source": "Kuntoutus, mielenterveyden ja käyttäytymisen häiriöt, yhteensä", "target": "Kuntoutus yhteensä, yhteensä", "value":0.544157464215311},{"source": "Kuntoutus, mielenterveyden ja käyttäytymisen häiriöt, yhteensä", "target": "Kuntoutus yhteensä, 16-19 v", "value":0.278531502562066},{"source": "Kuntoutus, mielenterveyden ja käyttäytymisen häiriöt, yhteensä", "target": "Kuntoutus yhteensä, 20-24 v", "value":0.227522432244437},{"source": "Kuntoutus, mielenterveyden ja käyttäytymisen häiriöt, yhteensä", "target": "Kuntoutus yhteensä, 25-29 v", "value":0.159060275672147},{"source": "Kuntoutus, mielenterveyden ja käyttäytymisen häiriöt, yhteensä", "target": "Kuntoutus yhteensä, 30-34 v", "value":0.379982293541071},{"source": "Kuntoutus, mielenterveyden ja käyttäytymisen häiriöt, yhteensä", "target": "Kuntoutus yhteensä, 35-39 v", "value":0.150479300383149},{"source": "Kuntoutus, mielenterveyden ja käyttäytymisen häiriöt, yhteensä", "target": "Kuntoutus yhteensä, 40-44 v", "value":0.163728633904494},{"source": "Kuntoutus, mielenterveyden ja käyttäytymisen häiriöt, yhteensä", "target": "Kuntoutus yhteensä, 45-49 v", "value":0.122733345161462},{"source": "Kuntoutus, mielenterveyden ja käyttäytymisen häiriöt, yhteensä", "target": "Kuntoutus yhteensä, 50-54 v", "value":0.172444797544002},{"source": "Kuntoutus, mielenterveyden ja käyttäytymisen häiriöt, yhteensä", "target": "Kuntoutus yhteensä, 55-59 v", "value":0.19284293696864},{"source": "Kuntoutus, mielenterveyden ja käyttäytymisen häiriöt, yhteensä", "target": "Kuntoutus, mielenterveyden ja käyttäytymisen häiriöt, 16-19 v", "value":0.310595417825868},{"source": "Kuntoutus, mielenterveyden ja käyttäytymisen häiriöt, yhteensä", "target": "Kuntoutus, mielenterveyden ja käyttäytymisen häiriöt, 20-24 v", "value":0.261356379042011},{"source": "Kuntoutus, mielenterveyden ja käyttäytymisen häiriöt, yhteensä", "target": "Kuntoutus, mielenterveyden ja käyttäytymisen häiriöt, 25-29 v", "value":0.160609338769511},{"source": "Kuntoutus, mielenterveyden ja käyttäytymisen häiriöt, yhteensä", "target": "Kuntoutus, mielenterveyden ja käyttäytymisen häiriöt, 30-34 v", "value":0.35152645441389},{"source": "Kuntoutus, mielenterveyden ja käyttäytymisen häiriöt, yhteensä", "target": "Kuntoutus, mielenterveyden ja käyttäytymisen häiriöt, 35-39 v", "value":0.329114496988952},{"source": "Kuntoutus, mielenterveyden ja käyttäytymisen häiriöt, yhteensä", "target": "Kuntoutus, mielenterveyden ja käyttäytymisen häiriöt, 40-44 v", "value":0.400837919049367},{"source": "Kuntoutus, mielenterveyden ja käyttäytymisen häiriöt, yhteensä", "target": "Kuntoutus, mielenterveyden ja käyttäytymisen häiriöt, 45-49 v", "value":0.175904243612069},{"source": "Kuntoutus, mielenterveyden ja käyttäytymisen häiriöt, yhteensä", "target": "Kuntoutus, mielenterveyden ja käyttäytymisen häiriöt, 50-54 v", "value":0.472541020410574},{"source": "Kuntoutus, mielenterveyden ja käyttäytymisen häiriöt, yhteensä", "target": "Kuntoutus, mielenterveyden ja käyttäytymisen häiriöt, 55-59 v", "value":0.329076884901029},{"source": "Kuntoutus, mielenterveyden ja käyttäytymisen häiriöt, yhteensä", "target": "Kuntoutus, muut kuin mielenterveys, 25-29 v", "value":-0.166261860552694}

]}