{"links":[

{"source": "Perusterveydenhuollon lääkärin asiakkaat 1-6 v", "target": "Avioliiton solmineet naiset 20-24", "value":0.119705530369743},{"source": "Perusterveydenhuollon lääkärin asiakkaat 1-6 v", "target": "Työllisyysaste, 60-64 -vuotiaat", "value":0.111981756179716},{"source": "Perusterveydenhuollon lääkärin asiakkaat 1-6 v", "target": "Työllisyysaste, 55-59 -vuotiaat", "value":0.121510685617053},{"source": "Perusterveydenhuollon lääkärin asiakkaat 1-6 v", "target": "Työllisyysaste, 45-54 -vuotiaat", "value":0.112819299897944},{"source": "Perusterveydenhuollon lääkärin asiakkaat 1-6 v", "target": "Koulukiusattuna vähintään kerran viikossa, % 8. ja 9. luokan oppilaista", "value":-0.129937317305282},{"source": "Perusterveydenhuollon lääkärin asiakkaat 1-6 v", "target": "Tulot/verot 60-64 -vuotiaat", "value":0.136790416988942},{"source": "Perusterveydenhuollon lääkärin asiakkaat 1-6 v", "target": "Työttömyysetuudet yli 60-vuotiaat", "value":-0.125763447564591},{"source": "Perusterveydenhuollon lääkärin asiakkaat 1-6 v", "target": "Perheisiin kuulumattomat 0-14-vuotiaat naiset", "value":0.122176724084313},{"source": "Perusterveydenhuollon lääkärin asiakkaat 1-6 v", "target": "Perheväestö 55-64-vuotiaat miehet", "value":0.126201166172539},{"source": "Perusterveydenhuollon lääkärin asiakkaat 1-6 v", "target": "Avioliitosta eronneet naiset 20-39-vuotiaat", "value":0.181765993542305},{"source": "Perusterveydenhuollon lääkärin asiakkaat 1-6 v", "target": "Miehet eronneet 20-29-vuotiaat", "value":0.138235692692898},{"source": "Perusterveydenhuollon lääkärin asiakkaat 1-6 v", "target": "Naiset naimisissa vieraskieliset 20-29-vuotiaat", "value":0.118547568874381},{"source": "Perusterveydenhuollon lääkärin asiakkaat 1-6 v", "target": "Pitkittyneesti perusturvan varassa, lapsia", "value":0.11949311207242},
{"source": "Perusterveydenhuollon lääkärin asiakkaat 1-6 v", "target": "Viranomaisten tehtävät", "value":0.146591033358924},{"source": "Perusterveydenhuollon lääkärin asiakkaat 1-6 v", "target": "Huumausainerikos, miehet", "value":0.490191715235802},{"source": "Perusterveydenhuollon lääkärin asiakkaat 1-6 v", "target": "Varkaus, naiset", "value":0.200841458011489},{"source": "Perusterveydenhuollon lääkärin asiakkaat 1-6 v", "target": "Kerrostalokauppojen lukumäärä", "value":0.217519745655484},{"source": "Perusterveydenhuollon lääkärin asiakkaat 1-6 v", "target": "Toisen asteen tutkinto miehet 60-64", "value":0.108884095984519},{"source": "Perusterveydenhuollon lääkärin asiakkaat 1-6 v", "target": "Korkea-asteen tutkinto naiset 65-69", "value":0.119016238378898},{"source": "Perusterveydenhuollon lääkärin asiakkaat 1-6 v", "target": "Aikuisten mielenterveyden avohoitokäynnit", "value":0.242148426131333},{"source": "Perusterveydenhuollon lääkärin asiakkaat 1-6 v", "target": "Maatilayritysten tulot", "value":-0.111048730690985},{"source": "Perusterveydenhuollon lääkärin asiakkaat 1-6 v", "target": "Ei perusasteen jälkeistä tutkintoa, naiset 1985-1989", "value":0.124425554261747},{"source": "Perusterveydenhuollon lääkärin asiakkaat 1-6 v", "target": "Työlliset, 55-59-vuotiaat", "value":0.154032173573857},{"source": "Perusterveydenhuollon lääkärin asiakkaat 1-6 v", "target": "Työlliset, 60-64-vuotiaat", "value":0.116552029139011},{"source": "Perusterveydenhuollon lääkärin asiakkaat 1-6 v", "target": "Väestö, kaupunkialueet", "value":-0.161830532118098},{"source": "Perusterveydenhuollon lääkärin asiakkaat 1-6 v", "target": "Työkyvyttömyyseläke, tuki- ja liikuntaelinten sairaudet 50-54 v", "value":-0.101865747977736},{"source": "Perusterveydenhuollon lääkärin asiakkaat 1-6 v", "target": "Työkyvyttömyyseläke, tuki- ja liikuntaelinten sairaudet 45-49 v", "value":0.154697301679811},{"source": "Perusterveydenhuollon lääkärin asiakkaat 1-6 v", "target": "Työkyvyttömyyseläke, tuki- ja liikuntaelinten sairaudet 40-44 v", "value":0.34162471929702},{"source": "Perusterveydenhuollon lääkärin asiakkaat 1-6 v", "target": "Työkyvyttömyyseläke, miehet 16-19 v", "value":0.148714047571091},{"source": "Perusterveydenhuollon lääkärin asiakkaat 1-6 v", "target": "Työkyvyttömyyseläke, miehet 20-24 v", "value":-0.101906987318614},{"source": "Perusterveydenhuollon lääkärin asiakkaat 1-6 v", "target": "Työkyvyttömyyseläke, miehet 40-44 v", "value":0.101793951819653},{"source": "Perusterveydenhuollon lääkärin asiakkaat 1-6 v", "target": "Työkyvyttömyyseläke, miehet 45-49 v", "value":-0.136381467201544},{"source": "Perusterveydenhuollon lääkärin asiakkaat 1-6 v", "target": "Työkyvyttömyyseläke, naiset 16-19 v", "value":-0.132596171482037},{"source": "Perusterveydenhuollon lääkärin asiakkaat 1-6 v", "target": "Keskimääräiset asumismenot €/kk kaikki lapsiperheet", "value":-0.107831866669507},{"source": "Perusterveydenhuollon lääkärin asiakkaat 1-6 v", "target": "Voimassaolevat lääkekorvausoikeudet 0-4 v", "value":0.151739458831455},{"source": "Perusterveydenhuollon lääkärin asiakkaat 1-6 v", "target": "Voimassaolevat lääkekorvausoikeudet 10-14 v", "value":-0.100161915049344},{"source": "Perusterveydenhuollon lääkärin asiakkaat 1-6 v", "target": "Kaikki eläkkeensaajat 30-34 v", "value":0.141983666790404},{"source": "Perusterveydenhuollon lääkärin asiakkaat 1-6 v", "target": "Kaikki eläkkeensaajat 65-69 v", "value":0.115464404412549},{"source": "Perusterveydenhuollon lääkärin asiakkaat 1-6 v", "target": "Työmarkkinatuki korvatut päivät yli 1000 miehet 20-24 v", "value":-0.790490957445211},{"source": "Perusterveydenhuollon lääkärin asiakkaat 1-6 v", "target": "Työmarkkinatuki korvatut päivät yli 1000 naiset 20-24 v", "value":-0.588365616071619},{"source": "Perusterveydenhuollon lääkärin asiakkaat 1-6 v", "target": "Työmarkkinatuki korvatut päivät yli 1000 miehet 30-34 v", "value":-0.163545938999101},{"source": "Perusterveydenhuollon lääkärin asiakkaat 1-6 v", "target": "Työmarkkinatuki korvatut päivät yli 1000 naiset 30-34 v", "value":0.212638192855043},{"source": "Perusterveydenhuollon lääkärin asiakkaat 1-6 v", "target": "Työmarkkinatuki korvatut päivät yli 1000 miehet 35-39 v", "value":-0.146296603039357},{"source": "Perusterveydenhuollon lääkärin asiakkaat 1-6 v", "target": "Työmarkkinatuki korvatut päivät yli 1000 miehet 55-59 v", "value":-0.123462610931371},{"source": "Perusterveydenhuollon lääkärin asiakkaat 1-6 v", "target": "Työmarkkinatuki korvatut päivät yli 1000 naiset 55-59 v", "value":-0.102687915326486},{"source": "Perusterveydenhuollon lääkärin asiakkaat 1-6 v", "target": "Erityishoitorahan saajat, lapset", "value":-0.114031385489936},{"source": "Perusterveydenhuollon lääkärin asiakkaat 1-6 v", "target": "Kuntoutus yhteensä, 30-34 v", "value":0.205109671284814},{"source": "Perusterveydenhuollon lääkärin asiakkaat 1-6 v", "target": "Kuntoutus yhteensä, 50-54 v", "value":0.100734482669621},{"source": "Perusterveydenhuollon lääkärin asiakkaat 1-6 v", "target": "Kuntoutus, mielenterveyden ja käyttäytymisen häiriöt, yhteensä", "value":0.110854733980672},{"source": "Perusterveydenhuollon lääkärin asiakkaat 1-6 v", "target": "Kuntoutus, mielenterveyden ja käyttäytymisen häiriöt, 30-34 v", "value":0.101764481560058},{"source": "Perusterveydenhuollon lääkärin asiakkaat 1-6 v", "target": "Kuntoutus, muut kuin mielenterveys, 20-24 v", "value":0.455671637541327}

]}